talisman_ie_ml_base-0.5.8.data/data/VERSION
tie_ml_base/__init__.py
tie_ml_base/env/__init__.py
tie_ml_base/helper/__init__.py
tie_ml_base/huggingface_pipeline/__init__.py
tie_ml_base/huggingface_pipeline/configuration.py
tie_ml_base/huggingface_pipeline/wrapper.py
tie_ml_base/huggingface_pipeline/normalization_wrapper/__init__.py
tie_ml_base/huggingface_pipeline/normalization_wrapper/abstract.py
tie_ml_base/huggingface_pipeline/normalization_wrapper/config.py
tie_ml_base/huggingface_pipeline/normalization_wrapper/string_normalizer.py
tie_ml_base/tools/__init__.py
tie_ml_base/torch_wrapper/__init__.py
talisman_ie_ml_base-0.5.8.dist-info/METADATA
talisman_ie_ml_base-0.5.8.dist-info/WHEEL
talisman_ie_ml_base-0.5.8.dist-info/entry_points.txt
talisman_ie_ml_base-0.5.8.dist-info/top_level.txt
talisman_ie_ml_base-0.5.8.dist-info/RECORD
